pyhartcmd/__init__.py
pyhartcmd/actions/__init__.py
pyhartcmd/actions/action.py
pyhartcmd/actions/action_dispatcher.py
pyhartcmd/actions/version.py
pyhartcmd/actions/example_action/__init__.py
pyhartcmd/actions/example_action/example_action.py
pyhartcmd/core/__init__.py
pyhartcmd/framework/__init__.py
pyhartcmd/framework/messages.py
pyhartcmd/main/__init__.py
pyhartcmd/main/main.py
pyhart-0.0.1.dist-info/METADATA
pyhart-0.0.1.dist-info/WHEEL
pyhart-0.0.1.dist-info/entry_points.txt
pyhart-0.0.1.dist-info/top_level.txt
pyhart-0.0.1.dist-info/RECORD
